pyicacls/__init__.py
pyicacls/attributes.py
pyicacls/getter.py
pyicacls/manager.py
pyicacls/permissions.py
pyicacls/setter.py
pyicacls/structs.py
pyicacls/examples/__init__.py
pyicacls/examples/icacls.py
pyicacls-1.1.2.dist-info/METADATA
pyicacls-1.1.2.dist-info/WHEEL
pyicacls-1.1.2.dist-info/top_level.txt
pyicacls-1.1.2.dist-info/RECORD
