Metadata-Version: 2.1
Name: pyicacls
Version: 1.1.2
Summary: A package to show and set windows files permissions
Home-page: https://github.com/gaffner/Pyicacls
Author: Gaffner
Author-email: gefen102@gmail.com
License: UNKNOWN
Platform: UNKNOWN
Classifier: Programming Language :: Python :: 3.9
Classifier: Programming Language :: Python :: 3.8
Classifier: License :: OSI Approved :: MIT License
Classifier: Operating System :: OS Independent
Requires-Dist: impacket (~=0.9.23)
